cybertron_framework/__init__.py
cybertron_framework/environment/__init__.py
cybertron_framework/environment/__tests__/__init__.py
cybertron_framework/environment/__tests__/test_environment.py
cybertron_framework/environment/__tests__/test_environment_interface.py
cybertron_framework/environment/environment.py
cybertron_framework/environment/environment_interface.py
cybertron_framework/exception/abort_process_exception.py
cybertron_framework/exception/no_data_to_process_exception.py
cybertron_framework/helper/__init__.py
cybertron_framework/helper/__tests__/__init__.py
cybertron_framework/helper/__tests__/test_benchmark.py
cybertron_framework/helper/__tests__/test_logger.py
cybertron_framework/helper/benchmark.py
cybertron_framework/helper/logger.py
cybertron_framework/input/input_manager_interface.py
cybertron_framework/orchestrator/__init__.py
cybertron_framework/orchestrator/__tests__/__init__.py
cybertron_framework/orchestrator/__tests__/test_abstract_orchestrator.py
cybertron_framework/orchestrator/abstract_orchestrator.py
cybertron_framework/orchestrator/orchestrator_interface.py
cybertron_framework/orchestrator/types/__init__.py
cybertron_framework/orchestrator/types/__tests__/__init__.py
cybertron_framework/orchestrator/types/__tests__/test_sequence.py
cybertron_framework/orchestrator/types/__tests__/test_synchronous.py
cybertron_framework/orchestrator/types/sequence.py
cybertron_framework/orchestrator/types/synchronous.py
cybertron_framework/output/__init__.py
cybertron_framework/output/__tests__/__init__.py
cybertron_framework/output/__tests__/test_output_manager_interface.py
cybertron_framework/output/output_manager_interface.py
cybertron_framework/transformer/__init__.py
cybertron_framework/transformer/__tests__/__init__.py
cybertron_framework/transformer/__tests__/test_transformer_manager_interface.py
cybertron_framework/transformer/transformer_manager_interface.py
cybertron_framework-0.0.2.dist-info/LICENSE
cybertron_framework-0.0.2.dist-info/METADATA
cybertron_framework-0.0.2.dist-info/WHEEL
cybertron_framework-0.0.2.dist-info/RECORD
