Metadata-Version: 2.1
Name: cybertron_framework
Version: 0.0.2
Summary: Cybertron is a framework intended for retrieving data from one or several repositories, transforming it, and storing in output repositories
Author: Making Science
Requires-Python: >=3.8.1,<4.0.0
Classifier: Programming Language :: Python :: 3
Classifier: Programming Language :: Python :: 3.9
Classifier: Programming Language :: Python :: 3.10
Classifier: Programming Language :: Python :: 3.11
Classifier: Programming Language :: Python :: 3.12
Requires-Dist: flake8 (>=6.0.0,<7.0.0)
Requires-Dist: freezegun (>=1.5.0,<2.0.0)
Requires-Dist: isort (>=5.12.0,<6.0.0)
Requires-Dist: pre-commit (>=3.1.1,<4.0.0)
